evolutions/__init__.py
evolutions/evolutions.py
evolutions-0.8.3.data/scripts/evolutions.py
evolutions-0.8.3.dist-info/LICENSE
evolutions-0.8.3.dist-info/METADATA
evolutions-0.8.3.dist-info/WHEEL
evolutions-0.8.3.dist-info/top_level.txt
evolutions-0.8.3.dist-info/RECORD
