Metadata-Version: 2.1
Name: evolutions
Version: 0.8.3
Summary: App framework agnostic pure SQL incremental database migrations tool modeled after play-evolutions
Home-page: https://github.com/arobertn/evolutions
Author: Adrian Robert
Author-email: arobert@interstitiality.net
License: BSD-3-Clause
Keywords: database migration sql python python3 evolutions
Platform: any
Classifier: Development Status :: 4 - Beta
Classifier: Intended Audience :: Developers
Classifier: Intended Audience :: System Administrators
Classifier: Topic :: Database
Classifier: License :: OSI Approved :: BSD License
Classifier: Programming Language :: Python :: 3
Requires-Python: >=3
License-File: LICENSE
